setup.py
modeflow/__init__.py
modeflow/modeflow.py
modeflow.egg-info/PKG-INFO
modeflow.egg-info/SOURCES.txt
modeflow.egg-info/dependency_links.txt
modeflow.egg-info/top_level.txt