Metadata-Version: 2.1
Name: modeflow
Version: 0.0.2
Summary: Flow support on the PyPi index
Author: VVDev
